changelog/.gitempty
dkist_processing_core/__init__.py
dkist_processing_core/build_utils.py
dkist_processing_core/config.py
dkist_processing_core/failure_callback.py
dkist_processing_core/node.py
dkist_processing_core/resource_queue.py
dkist_processing_core/task.py
dkist_processing_core/workflow.py
dkist_processing_core/tests/__init__.py
dkist_processing_core/tests/conftest.py
dkist_processing_core/tests/task_example.py
dkist_processing_core/tests/test_build_utils.py
dkist_processing_core/tests/test_export.py
dkist_processing_core/tests/test_failure_callback.py
dkist_processing_core/tests/test_node.py
dkist_processing_core/tests/test_task.py
dkist_processing_core/tests/test_workflow.py
dkist_processing_core/tests/invalid_workflow_cyclic/__init__.py
dkist_processing_core/tests/invalid_workflow_cyclic/workflow.py
dkist_processing_core/tests/invalid_workflow_for_docker_multi_category/__init__.py
dkist_processing_core/tests/invalid_workflow_for_docker_multi_category/workflow.py
dkist_processing_core/tests/valid_workflow_package/__init__.py
dkist_processing_core/tests/valid_workflow_package/workflow.py
dkist_processing_core/tests/zero_node_workflow_package/__init__.py
dkist_processing_core/tests/zero_node_workflow_package/workflow.py
docs/Makefile
docs/auto-proc-concept-model.png
docs/auto_proc_brick.png
docs/automated-processing-deployed.png
docs/changelog.rst
docs/conf.py
docs/index.rst
docs/landing_page.rst
docs/make.bat
docs/requirements.txt
licenses/LICENSE.rst
dkist_processing_core-6.0.1.dist-info/METADATA
dkist_processing_core-6.0.1.dist-info/WHEEL
dkist_processing_core-6.0.1.dist-info/top_level.txt
dkist_processing_core-6.0.1.dist-info/RECORD
