Metadata-Version: 2.4
Name: dkist-processing-core
Version: 6.0.1
Summary: Abstraction layer used by the DKIST science data processing pipelines with Apache Airflow
Author-email: NSO / AURA <dkistdc@nso.edu>
License: BSD-3-Clause
Project-URL: Homepage, https://nso.edu/dkist/data-center/
Project-URL: Repository, https://bitbucket.org/dkistdc/dkist-processing-core/
Project-URL: Documentation, https://docs.dkist.nso.edu/projects/core
Project-URL: Help, https://nso.atlassian.net/servicedesk/customer/portal/5
Classifier: Programming Language :: Python
Classifier: Programming Language :: Python :: 3
Classifier: Programming Language :: Python :: 3.12
Requires-Python: >=3.12
Requires-Dist: apache-airflow[celery,postgres]==2.11.0
Requires-Dist: requests>=2.23
Requires-Dist: talus<2.0,>=1.3.4
Requires-Dist: pendulum
Requires-Dist: nbformat>=5.9.2
Requires-Dist: dkist-service-configuration<5.0,>=4.1.13
Requires-Dist: pydantic>2.0
Provides-Extra: test
Requires-Dist: pytest; extra == "test"
Requires-Dist: pytest-cov; extra == "test"
Requires-Dist: pytest-mock; extra == "test"
Requires-Dist: jinja2; extra == "test"
Requires-Dist: towncrier; extra == "test"
Requires-Dist: nbconvert; extra == "test"
Requires-Dist: ipython; extra == "test"
Provides-Extra: docs
Requires-Dist: sphinx; extra == "docs"
Requires-Dist: sphinx-astropy; extra == "docs"
Requires-Dist: sphinx-changelog; extra == "docs"
Requires-Dist: sphinx-autoapi; extra == "docs"
Requires-Dist: pytest; extra == "docs"
Requires-Dist: towncrier; extra == "docs"
Requires-Dist: dkist-sphinx-theme; extra == "docs"
Requires-Dist: matplotlib; extra == "docs"
Requires-Dist: sunpy; extra == "docs"
